LICENSE
MANIFEST.in
README.md
pyproject.toml
setup.py
surfacetopology/__init__.py
surfacetopology/halfedges.cpp
surfacetopology/halfedges.h
surfacetopology/topology.cpp
surfacetopology/topology.pyx
surfacetopology/trisurftopology.cpp
surfacetopology/trisurftopology.h
surfacetopology/unionfind.cpp
surfacetopology/unionfind.h
surfacetopology/wrapper.py
surfacetopology.egg-info/PKG-INFO
surfacetopology.egg-info/SOURCES.txt
surfacetopology.egg-info/dependency_links.txt
surfacetopology.egg-info/not-zip-safe
surfacetopology.egg-info/requires.txt
surfacetopology.egg-info/top_level.txt