Metadata-Version: 2.1
Name: surfacetopology
Version: 0.1.2
Summary: Check the validity and determine the topology of a triangulated surface
Home-page: https://github.com/jacquemv/surfacetopology
Author: Vincent Jacquemet
Author-email: vincent.jacquemet@umontreal.ca
License: MIT
Keywords: triangular,mesh,surface,manifold,boundary,orientability,genus
License-File: LICENSE
